LICENSE
MANIFEST.in
README.rst
doc-requirements.txt
requirements.txt
setup.cfg
setup.py
test-requirements.txt
versioneer.py
rmdex/__init__.py
rmdex/_version.py
rmdex/cli.py
rmdex/exerciser.py
rmdex.egg-info/PKG-INFO
rmdex.egg-info/SOURCES.txt
rmdex.egg-info/dependency_links.txt
rmdex.egg-info/entry_points.txt
rmdex.egg-info/requires.txt
rmdex.egg-info/top_level.txt
rmdex/tests/__init__.py
rmdex/tests/test_exerciser.py
rmdex/tests/test_scripts.py