Metadata-Version: 2.1
Name: rmdex
Version: 0.1
Summary: Utilities to process exercises in RMarkdown notebooks
Home-page: http://github.com/matthew-brett/rmdex
Author: Matthew Brett
Author-email: matthew.brett@gmail.com
Maintainer: Matthew Brett
Maintainer-email: matthew.brett@gmail.com
License: BSD license
Platform: UNKNOWN
Classifier: Development Status :: 3 - Alpha
Classifier: Environment :: Console
Classifier: Intended Audience :: Developers
Classifier: Intended Audience :: Science/Research
Classifier: License :: OSI Approved :: BSD License
Classifier: Programming Language :: Python :: 3
Classifier: Programming Language :: Python :: 3.6
Classifier: Programming Language :: Python :: 3.7
Classifier: Programming Language :: Python :: 3.8
Classifier: Topic :: Scientific/Engineering
Classifier: Operating System :: Microsoft :: Windows
Classifier: Operating System :: POSIX
Classifier: Operating System :: Unix
Classifier: Operating System :: MacOS
Requires-Python: >=3.6
Provides-Extra: test
